cuitools/__init__.py
cuitools/subp.py
cuitools-1.6.6.dist-info/METADATA
cuitools-1.6.6.dist-info/WHEEL
cuitools-1.6.6.dist-info/top_level.txt
cuitools-1.6.6.dist-info/RECORD
