Metadata-Version: 2.1
Name: cuitools
Version: 1.6.6
Summary: Provides CUI drawing support libraries.
Home-page: https://github.com/kumitatepazuru/cuitools
Author: kumitatepazuru
Author-email: teltelboya18@gmail.com
Maintainer: kumitatepazuru
Maintainer-email: teltelboya18@gmail.com
License: MIT
Platform: UNKNOWN
Classifier: Programming Language :: Python :: 3 :: Only
Classifier: License :: OSI Approved :: MIT License
